itk/LabelPointSetPython.py
itk/_LabelPointSetPython.pyd
itk/__init_labelpointset__.py
itk/itkLabelToPointSetFilterPython.py
itk/Configuration/LabelPointSetConfig.py
itk/Configuration/LabelPointSet_snake_case.py
itk_labelpointset-0.3.0.dist-info/licenses/LICENSE
itk_labelpointset.libs/msvcp140.dll
itk_labelpointset.libs/tbb12.dll
itk_labelpointset-0.3.0.dist-info/DELVEWHEEL
itk_labelpointset-0.3.0.dist-info/METADATA
itk_labelpointset-0.3.0.dist-info/WHEEL
itk_labelpointset-0.3.0.dist-info/RECORD
